demo/__init__.py
demo/pub.py
demo/run.py
demo/page/__init__.py
demo/page/adr_page.py
demo/page/image_page.py
demo/page/ios_page.py
demo/page/mac_page.py
demo/page/ocr_page.py
demo/page/web_page.py
demo/page/win_page.py
demo/pages/__init__.py
demo/pages/adr_page.py
demo/pages/ios_page.py
demo/pages/web_page.py
demo/test/__init__.py
demo/test/adr_script.py
demo/test/test_adr.py
demo/test/test_api.py
demo/test/test_image.py
demo/test/test_ios.py
demo/test/test_ocr.py
demo/test/test_para.py
demo/test/test_web.py
demo/tests/__init__.py
demo/tests/adr_script.py
demo/tests/test_adr.py
demo/tests/test_api.py
demo/tests/test_image.py
demo/tests/test_ios.py
demo/tests/test_mac.py
demo/tests/test_ocr.py
demo/tests/test_para.py
demo/tests/test_web.py
demo/tests/test_win.py
kuto/__init__.py
kuto/case.py
kuto/cli.py
kuto/general.py
kuto/page.py
kuto/scaffold.py
kuto/android/__init__.py
kuto/android/case.py
kuto/android/common.py
kuto/android/driver.py
kuto/android/element.py
kuto/api/__init__.py
kuto/api/case.py
kuto/api/request.py
kuto/core/__init__.py
kuto/core/android/__init__.py
kuto/core/android/common.py
kuto/core/android/driver.py
kuto/core/android/element.py
kuto/core/api/__init__.py
kuto/core/api/request.py
kuto/core/h5/__init__.py
kuto/core/h5/driver.py
kuto/core/image/__init__.py
kuto/core/image/driver.py
kuto/core/image/element.py
kuto/core/image/image_discern.py
kuto/core/image_discern/__init__.py
kuto/core/image_discern/driver.py
kuto/core/image_discern/element.py
kuto/core/ios/__init__.py
kuto/core/ios/common.py
kuto/core/ios/driver.py
kuto/core/ios/element.py
kuto/core/mac/__init__.py
kuto/core/mac/driver.py
kuto/core/mac/element.py
kuto/core/ocr/__init__.py
kuto/core/ocr/driver.py
kuto/core/ocr/element.py
kuto/core/ocr/ocr_discern.py
kuto/core/ocr/test_cut.py
kuto/core/ocr_discern/__init__.py
kuto/core/ocr_discern/driver.py
kuto/core/ocr_discern/element.py
kuto/core/sonic/__init__.py
kuto/core/sonic/sib_util.py
kuto/core/web/__init__.py
kuto/core/web/driver.py
kuto-0.0.75.dist-info/METADATA
kuto-0.0.75.dist-info/WHEEL
kuto-0.0.75.dist-info/entry_points.txt
kuto-0.0.75.dist-info/top_level.txt
kuto-0.0.75.dist-info/RECORD
