Metadata-Version: 2.1
Name: kuto
Version: 0.0.75
Summary: 全平台自动化测试框架
Home-page: https://gitee.com/bluepang2021/kuto
Author: 杨康
Author-email: 772840356@qq.com
Platform: Android
Platform: IOS
Platform: Web
Platform: Api
Platform: Mac
Platform: Win
Classifier: Programming Language :: Python :: 3.9
Requires-Python: >=3.9
Requires-Dist: requests-toolbelt (==0.10.1)
Requires-Dist: jmespath (==0.9.5)
Requires-Dist: jsonschema (==4.17.0)
Requires-Dist: pytest (==6.2.5)
Requires-Dist: pytest-rerunfailures (==10.2)
Requires-Dist: pytest-xdist (==2.5.0)
Requires-Dist: allure-pytest (==2.9.45)
Requires-Dist: click (~=8.1.3)
Requires-Dist: loguru (==0.7.0)
Requires-Dist: urllib3 (==1.26.15)
Requires-Dist: PyYAML (~=6.0)
Provides-Extra: app
Requires-Dist: uiautomator2 (==2.16.23) ; extra == 'app'
Requires-Dist: tidevice (==0.6.1) ; extra == 'app'
Requires-Dist: facebook-wda (==1.4.6) ; extra == 'app'
Requires-Dist: opencv-python (==4.6.0.66) ; extra == 'app'
Requires-Dist: easyocr (==1.7.0) ; extra == 'app'
Requires-Dist: Pillow (==9.5.0) ; extra == 'app'
Requires-Dist: filelock (==3.12.2) ; extra == 'app'
Provides-Extra: encrypt
Requires-Dist: pycryptodome (==3.14.1) ; extra == 'encrypt'
Provides-Extra: excel
Requires-Dist: pandas (==1.3.4) ; extra == 'excel'
Requires-Dist: openpyxl (==3.0.9) ; extra == 'excel'
Requires-Dist: XlsxWriter (==3.0.2) ; extra == 'excel'
Provides-Extra: pc
Requires-Dist: PyAutoGUI (==0.9.54) ; extra == 'pc'
Requires-Dist: opencv-python (==4.6.0.66) ; extra == 'pc'
Provides-Extra: web
Requires-Dist: playwright (==1.33.0) ; extra == 'web'
Requires-Dist: opencv-python (==4.6.0.66) ; extra == 'web'
